data_bench/__init__.py
data_bench/exceptions.py
data_bench/scheduler.py
data_bench/transaction.py
data_bench/utility/__init__.py
data_bench/utility/clihelper.py
data_bench/utility/loggedobject.py
data_bench/utility/tests/__init__.py
data_bench/utility/tests/utility.py
data_bench-0.5.0.dist-info/DESCRIPTION.rst
data_bench-0.5.0.dist-info/METADATA
data_bench-0.5.0.dist-info/RECORD
data_bench-0.5.0.dist-info/WHEEL
data_bench-0.5.0.dist-info/metadata.json
data_bench-0.5.0.dist-info/top_level.txt
data_bench-0.5.0.dist-info/zip-safe
