Metadata-Version: 2.0
Name: data-bench
Version: 0.5.0
Summary: Data Bench Python module for building consumers/producers.
Home-page: https://github.com/Data-Bench/data-bench-python
Author: Erik O'Shaughnessy
Author-email: erik.oshaughnessy@intel.com
License: Apache License, Version 2.0
Keywords: data_bench development kafka
Platform: any
Classifier: Development Status :: 3 - Alpha
Classifier: Environment :: Console
Classifier: Intended Audience :: Developers
Classifier: Programming Language :: Python
Classifier: Programming Language :: Python :: 3
Classifier: Programming Language :: Python :: 3.3
Classifier: Programming Language :: Python :: 3.4
Classifier: Programming Language :: Python :: 3.5
Classifier: Programming Language :: Python :: 3.6
Classifier: Programming Language :: Python :: Implementation :: PyPy
Classifier: Topic :: Software Development :: Libraries :: Python Modules
Classifier: Topic :: Utilities
Classifier: License :: OSI Approved :: Apache Software License
